{"metadata": {"dbt_schema_version": "https://schemas.getdbt.com/dbt/run-results/v5.json", "dbt_version": "1.7.4", "generated_at": "2024-01-04T06:19:11.176854Z", "invocation_id": "ea80008c-24da-4632-9270-db41160d6116", "env": {}}, "results": [{"status": "success", "timing": [{"name": "compile", "started_at": "2024-01-04T06:19:07.259454Z", "completed_at": "2024-01-04T06:19:07.295089Z"}, {"name": "execute", "started_at": "2024-01-04T06:19:07.296515Z", "completed_at": "2024-01-04T06:19:10.668343Z"}], "thread_id": "Thread-1", "execution_time": 3.9149320125579834, "adapter_response": {"_message": "SUCCESS 500", "code": "SUCCESS", "rows_affected": 500, "query_id": "01b1703b-3200-f92d-0006-f46e0002d016"}, "message": null, "failures": null, "unique_id": "model.pricesmart.raw_customer", "compiled": true, "compiled_code": "\n  \n    select *\n    from (\n        \n\nSelect *\nfrom RAW.PRICESMART.CUSTOMERS\n    ) as model_limit_subq\n    limit 500\n\n", "relation_name": "RAW.pricesmart.raw_customer"}], "elapsed_time": 3.955456018447876, "args": {"project_dir": "/usr/src/develop/user-248518/environment-268239/repository-199479", "warn_error_options": {"include": [], "exclude": []}, "exclude": [], "quiet": true, "which": "show", "profile": "user", "partial_parse_file_diff": true, "log_path": "/usr/src/dbt-server-shared/working_dir/b167a0c7-efb2-425b-b817-572102427498", "write_json": true, "show_resource_report": false, "introspect": true, "defer": false, "static_parser": true, "use_colors": true, "populate_cache": false, "log_level_file": "debug", "select": ["models/raw/raw_customer.sql"], "favor_state": false, "enable_legacy_logger": false, "print": true, "invocation_command": "dbt -A dbt_worker.app worker --loglevel=DEBUG --concurrency=2 --max-memory-per-child=500000", "partial_parse": true, "limit": 500, "send_anonymous_usage_stats": true, "log_level": "info", "log_format": "json", "log_format_file": "json", "strict_mode": false, "vars": {}, "version_check": true, "printer_width": 80, "output": "json", "profiles_dir": "/usr/src/dbt-server-shared/.dbt", "indirect_selection": "empty", "macro_debugging": false, "use_colors_file": true, "cache_selected_only": false, "log_file_max_bytes": 0}}